{
  "ADM 0800100_0733_2025 de 30_09_2025.PDF": {
    "total_aparelhos": 13,
    "total_linhas": 2,
    "total_valor": 53482.98
  },
  "ADM 0800100_0734_2025 de 30_09_2025.PDF": {
    "total_aparelhos": 6879,
    "total_linhas": 832,
    "total_valor": 29417494.99
  },
  "ADM 0800100_0735_2025 de 30_09_2025.PDF": {
    "total_aparelhos": 3804,
    "total_linhas": 431,
    "total_valor": 14861805.46
  },
  "ADM 0800100_0736_2025 de 30_09_2025.PDF": {
    "total_aparelhos": 1873,
    "total_linhas": 116,
    "total_valor": 6331281.1
  },
  "ADM 0800100_0737_2025 de 30_09_2025.PDF": {
    "total_aparelhos": 616,
    "total_linhas": 616,
    "total_valor": 280644.01
  },
  "ADM 0800100_0738_2025 de 30_09_2025.PDF": {
    "total_aparelhos": 442,
    "total_linhas": 442,
    "total_valor": 485270.26
  },
  "ADM 0800100_0739_2025 de 30_09_2025.PDF": {
    "total_aparelhos": 3708,
    "total_linhas": 3651,
    "total_valor": 1894061.14
  },
  "ADM 0800100_0740_2025 de 30_09_2025.PDF": {
    "total_aparelhos": 9,
    "total_linhas": 6,
    "total_valor": 5746.52
  },
  "ADM 0800100_0741_2025 de 30_09_2025.PDF": {
    "total_aparelhos": 19,
    "total_linhas": 19,
    "total_valor": 18816.2
  },
  "ADM 0800100_0742_2025 de 30_09_2025.PDF": {
    "total_aparelhos": 225,
    "total_linhas": 163,
    "total_valor": 225352.99
  },
  "ADM 0800100_0743_2025 de 30_09_2025.PDF": {
    "total_aparelhos": 910,
    "total_linhas": 411,
    "total_valor": 3007322.26
  },
  "ADM 0800100_0744_2025 de 30_09_2025.PDF": {
    "total_aparelhos": 3457,
    "total_linhas": 3457,
    "total_valor": 3461458.49
  },
  "ADM 0800100_0745_2025 de 30_09_2025.PDF": {
    "total_aparelhos": 3390,
    "total_linhas": 2300,
    "total_valor": 13344984.26
  },
  "ADM 0800100_0746_2025 de 30_09_2025.PDF": {
    "total_aparelhos": 2544,
    "total_linhas": 1355,
    "total_valor": 4603282.61
  },
  "ADM 0800100_0747_2025 de 30092025.PDF": {
    "total_aparelhos": 4124,
    "total_linhas": 667,
    "total_valor": 24802164.25
  }
}